setup.py
pyps/__init__.py
pyps/agilent.py
pyps/base.py
pyps/conrad_relay.py
pyps/ea.py
pyps/gwinstek.py
pyps/plot.py
pyps/tti.py
pyps/voltcraft.py
pyps/winioctl.py
pytty/SerTty.py
pytty/__init__.py
pyuds/__init__.py
pyuds.egg-info/PKG-INFO
pyuds.egg-info/SOURCES.txt
pyuds.egg-info/dependency_links.txt
pyuds.egg-info/not-zip-safe
pyuds.egg-info/requires.txt
pyuds.egg-info/top_level.txt
pyuds/PyUds/CanTp.py
pyuds/PyUds/ComBase.py
pyuds/PyUds/FrTp.py
pyuds/PyUds/FrameManage.py
pyuds/PyUds/MsgManage.py
pyuds/PyUds/UdsBase.py
pyuds/PyUds/__init__.py
pyuds/PyUds/bus/__init__.py
pyuds/PyUds/bus/can.py
pyuds/PyUds/bus/fr.py
pyuds/PyUds/bus/driver/__init__.py
pyuds/PyUds/bus/driver/pcan/__init__.py
pyuds/PyUds/bus/driver/pcan/basic.py
pyuds/PyUds/bus/driver/pcan/pcan.py
pyuds/PyUds/bus/driver/vector/__init__.py
pyuds/PyUds/bus/driver/vector/vxl_can.py
pyuds/PyUds/bus/driver/vector/vxl_fr.py
pyuds/PyUds/bus/driver/vector/vxlapy.py
pyuds/PyUds/bus/driver/vector/vxlbase.py
pyuds/PyUds/log/__init__.py
pyuds/PyUds/wres/__init__.py
pyuds/Scripts/BaseType.py
pyuds/Scripts/JsonConfig.py
pyuds/Scripts/SecurityKey.py
pyuds/Scripts/__init__.py
pyuds/TestCase/MsgBaseTest.py
pyuds/TestCase/UdsBaseTest.py
pyuds/TestCase/__init__.py
pyuds/TestCase/Report/Report.py
pyuds/TestCase/Report/UdsLog.py
pyuds/TestCase/Report/__init__.py